wejr/apps.py
wejr/consumers.py
wejr/jsonrpc/constants.py
wejr/jsonrpc/errors.py
wejr/jsonrpc/exceptions.py
wejr/jsonrpc/request.py
wejr/jsonrpc/response.py
wejr/router.py
wejr/utils/common.py
wejr-0.1.1.dist-info/METADATA
wejr-0.1.1.dist-info/WHEEL
wejr-0.1.1.dist-info/RECORD
