Metadata-Version: 2.1
Name: wejr
Version: 0.1.1
Summary: Communication via websocket in JSON-RPC way
Author: Wasth
Author-email: riasta@yandex.ru
Requires-Python: >=3.10,<4.0
Classifier: Programming Language :: Python :: 3
Classifier: Programming Language :: Python :: 3.10
Classifier: Programming Language :: Python :: 3.11
Provides-Extra: redis
Requires-Dist: channels (>=4.0.0,<5.0.0)
Requires-Dist: channels-redis (>=4.0.0,<5.0.0) ; extra == "redis"
